pynbp/__init__.py
pynbp-0.0.9.dist-info/LICENSE
pynbp-0.0.9.dist-info/METADATA
pynbp-0.0.9.dist-info/WHEEL
pynbp-0.0.9.dist-info/top_level.txt
pynbp-0.0.9.dist-info/RECORD
