Metadata-Version: 2.1
Name: pynbp
Version: 0.0.9
Summary: Python implementation of the HP Tuners Track Addict Numeric Broadcast Protocol (V1.0)
Home-page: https://github.com/tmkdev/pynbp
Author: Terry Kolody
Author-email: tekolody@gmail.com
License: UNKNOWN
Platform: UNKNOWN
Classifier: Programming Language :: Python :: 3
Classifier: License :: OSI Approved :: MIT License
Classifier: Operating System :: OS Independent
Requires-Python: >=3
Requires-Dist: pyserial
